starlette_htmx/__init__.py
starlette_htmx/middleware.py
starlette_htmx-0.1.1.dist-info/LICENSE
starlette_htmx-0.1.1.dist-info/WHEEL
starlette_htmx-0.1.1.dist-info/METADATA
starlette_htmx-0.1.1.dist-info/RECORD
