Metadata-Version: 2.1
Name: starlette_htmx
Version: 0.1.1
Summary: Extensions for using HTMX with Starlette
Author-email: Felix Ingram <f.ingram@gmail.com>
Classifier: License :: OSI Approved :: MIT License
Requires-Dist: starlette
Project-URL: Home, https://github.com/lllama/starlette-htmx
